area_calculator_se.py
area_calculator_se-0.0.2.dist-info/LICENSE
area_calculator_se-0.0.2.dist-info/METADATA
area_calculator_se-0.0.2.dist-info/WHEEL
area_calculator_se-0.0.2.dist-info/top_level.txt
area_calculator_se-0.0.2.dist-info/RECORD
