Metadata-Version: 2.1
Name: area-calculator-se
Version: 0.0.2
Summary: Calculate areas of geometrical figures
Author: Saeideh Eslamian
Classifier: Programming Language :: Python :: 3
Classifier: License :: OSI Approved :: MIT License
Classifier: Operating System :: OS Independent
Requires-Python: >=3.6
License-File: LICENSE
